CINI_selector-0.0.5.data/data/requirements.txt
CINI_selector-0.0.5.data/data/.git/config
cini_selector/__init__.py
cini_selector/CONFIG_FILE/CINI_Configuration_File.json
CINI_selector-0.0.5.dist-info/LICENSE
CINI_selector-0.0.5.dist-info/METADATA
CINI_selector-0.0.5.dist-info/WHEEL
CINI_selector-0.0.5.dist-info/top_level.txt
CINI_selector-0.0.5.dist-info/RECORD
